i3razer/__init__.py
i3razer/config_contants.py
i3razer/config_parser.py
i3razer/example_config.yaml
i3razer/i3_razer.py
i3razer/layout.py
i3razer/map_layout.py
i3razer/pyxhook.py
i3razer-0.2.dist-info/LICENSE
i3razer-0.2.dist-info/METADATA
i3razer-0.2.dist-info/WHEEL
i3razer-0.2.dist-info/dependency_links.txt
i3razer-0.2.dist-info/entry_points.txt
i3razer-0.2.dist-info/top_level.txt
i3razer-0.2.dist-info/RECORD
