Metadata-Version: 2.1
Name: i3razer
Version: 0.2
Summary: Shortcut/Command visualization on razer keyboards via openrazer
Home-page: https://github.com/leofah/i3razer
Author: Leo Fahrbach
Author-email: 
License: MIT
Platform: UNKNOWN
Classifier: Development Status :: 3 - Alpha
Classifier: Programming Language :: Python :: 3
Classifier: License :: OSI Approved :: MIT License
Classifier: Operating System :: POSIX :: Linux
Requires-Python: >=3
License-File: LICENSE
Requires-Dist: xlib (>=0.21)
Requires-Dist: PyYAML (>=5.3.1)
